lynx_e2e/__init__.py
lynx_e2e/__version__.py
lynx_e2e/_impl/__init__.py
lynx_e2e/_impl/config.py
lynx_e2e/_impl/exception.py
lynx_e2e/_impl/utils.py
lynx_e2e/_impl/appium/__init__.py
lynx_e2e/_impl/appium/app.py
lynx_e2e/_impl/appium/device.py
lynx_e2e/_impl/appium/device_driver.py
lynx_e2e/_impl/appium/lynx_element.py
lynx_e2e/_impl/appium/lynx_view.py
lynx_e2e/_impl/core/__init__.py
lynx_e2e/_impl/core/app.py
lynx_e2e/_impl/core/debugger.py
lynx_e2e/_impl/core/document_tree.py
lynx_e2e/_impl/core/element_searcher.py
lynx_e2e/_impl/core/lynx_driver.py
lynx_e2e/_impl/core/lynx_element_mixin.py
lynx_e2e/_impl/core/lynx_view_mixin.py
lynx_e2e/_impl/core/rectangle.py
lynx_e2e/_impl/core/upath.py
lynx_e2e/_impl/core/utils.py
lynx_e2e/_impl/core/debugger_mixin/__init__.py
lynx_e2e/_impl/core/debugger_mixin/dom.py
lynx_e2e/_impl/core/debugger_mixin/performance.py
lynx_e2e/_impl/core/debugger_mixin/runtime.py
lynx_e2e/_impl/core/debugger_mixin/screencast.py
lynx_e2e/_impl/core/debugger_mixin/testbench.py
lynx_e2e/_impl/core/logger/__init__.py
lynx_e2e/_impl/core/logger/cdp_logger.py
lynx_e2e/_impl/core/logger/console_logger.py
lynx_e2e/_impl/core/net/__init__.py
lynx_e2e/_impl/core/net/base_connector.py
lynx_e2e/_impl/core/net/receiver.py
lynx_e2e/_impl/core/net/sender.py
lynx_e2e/_impl/core/net/usb_connector.py
lynx_e2e/_impl/device/__init__.py
lynx_e2e/_impl/device/android_device_driver_mixin.py
lynx_e2e/_impl/device/device.py
lynx_e2e/_impl/device/device_driver.py
lynx_e2e/_impl/device/exception.py
lynx_e2e/_impl/device/ios_device_driver_mixin.py
lynx_e2e/_impl/device/resource.py
lynx_e2e/_impl/device/adb/__init__.py
lynx_e2e/_impl/device/adb/adb.py
lynx_e2e/_impl/device/adb/adb_client.py
lynx_e2e/_impl/device/adb/exception.py
lynx_e2e/_impl/manage/__init__.py
lynx_e2e/_impl/manage/case_runner.py
lynx_e2e/_impl/manage/exception.py
lynx_e2e/_impl/manage/loader.py
lynx_e2e/_impl/manage/management.py
lynx_e2e/_impl/manage/report.py
lynx_e2e/_impl/manage/test_result.py
lynx_e2e_appium-0.0.8.dist-info/LICENSE
lynx_e2e_appium-0.0.8.dist-info/METADATA
lynx_e2e_appium-0.0.8.dist-info/WHEEL
lynx_e2e_appium-0.0.8.dist-info/top_level.txt
lynx_e2e_appium-0.0.8.dist-info/RECORD
