Metadata-Version: 2.1
Name: lynx-e2e-appium
Version: 0.0.8
Summary: Lynx E2E Driver
Author: gaohanqing
Author-email: gaohqnuaa@foxmail.com
License-File: LICENSE
Requires-Dist: appium-python-client==3.1.1
Requires-Dist: selenium==4.17.2
Requires-Dist: ujson
Requires-Dist: opencv-python
